earwax/__init__.py
earwax/action.py
earwax/action_map.py
earwax/ambiance.py
earwax/config.py
earwax/configuration.py
earwax/credit.py
earwax/dialogue_tree.py
earwax/die.py
earwax/editor.py
earwax/event_matcher.py
earwax/game.py
earwax/game_board.py
earwax/hat_directions.py
earwax/input_modes.py
earwax/level.py
earwax/mixins.py
earwax/networking.py
earwax/point.py
earwax/pyglet.py
earwax/reverb.py
earwax/rumble_effects.py
earwax/sdl.py
earwax/sound.py
earwax/speech.py
earwax/task.py
earwax/track.py
earwax/types.py
earwax/utils.py
earwax/vault_file.py
earwax/walking_directions.py
earwax/yaml.py
earwax/cmd/__init__.py
earwax/cmd/blank_game.py
earwax/cmd/constants.py
earwax/cmd/game_level.py
earwax/cmd/keys.py
earwax/cmd/main.py
earwax/cmd/project.py
earwax/cmd/project_credit.py
earwax/cmd/variable.py
earwax/cmd/subcommands/__init__.py
earwax/cmd/subcommands/configure_earwax.py
earwax/cmd/subcommands/game.py
earwax/cmd/subcommands/game_map.py
earwax/cmd/subcommands/init_project.py
earwax/cmd/subcommands/story.py
earwax/cmd/subcommands/vault.py
earwax/mapping/__init__.py
earwax/mapping/box.py
earwax/mapping/box_level.py
earwax/mapping/door.py
earwax/mapping/map_editor.py
earwax/mapping/portal.py
earwax/menus/__init__.py
earwax/menus/action_menu.py
earwax/menus/config_menu.py
earwax/menus/file_menu.py
earwax/menus/menu.py
earwax/menus/menu_item.py
earwax/menus/reverb_editor.py
earwax/promises/__init__.py
earwax/promises/base.py
earwax/promises/staggered_promise.py
earwax/promises/threaded_promise.py
earwax/story/__init__.py
earwax/story/context.py
earwax/story/edit_level.py
earwax/story/play_level.py
earwax/story/world.py
earwax-2026.2.8.dist-info/AUTHORS
earwax-2026.2.8.dist-info/LICENSE
earwax-2026.2.8.dist-info/METADATA
earwax-2026.2.8.dist-info/WHEEL
earwax-2026.2.8.dist-info/entry_points.txt
earwax-2026.2.8.dist-info/pbr.json
earwax-2026.2.8.dist-info/top_level.txt
earwax-2026.2.8.dist-info/RECORD
